omnicli_sphinx/__init__.py
omnicli_sphinx/plugin.py
omnicli_sphinx-0.0.1.dist-info/METADATA
omnicli_sphinx-0.0.1.dist-info/WHEEL
omnicli_sphinx-0.0.1.dist-info/licenses/LICENSE
omnicli_sphinx-0.0.1.dist-info/RECORD
