Metadata-Version: 2.3
Name: omnicli-sphinx
Version: 0.0.1
Summary: Sphinx extension for documenting Omni commands
Project-URL: Homepage, https://omnicli.dev
Project-URL: Documentation, https://omnicli.dev
Project-URL: Repository, https://github.com/omnicli/sphinx-extension.git
Project-URL: Issues, https://github.com/omnicli/sphinx-extension/issues
Project-URL: Changelog, https://github.com/omnicli/sphinx-extension/commits/main/
Author-email: Raphaël Beamonte <raphael.beamonte@gmail.com>
License: MIT License
Keywords: cli,documentation,omni,omnicli,sphinx
Classifier: Framework :: Sphinx
Classifier: Framework :: Sphinx :: Extension
Classifier: License :: OSI Approved :: MIT License
Classifier: Programming Language :: Python :: 3
Classifier: Programming Language :: Python :: 3.8
Classifier: Programming Language :: Python :: 3.9
Classifier: Programming Language :: Python :: 3.10
Classifier: Programming Language :: Python :: 3.11
Requires-Python: >=3.8
Requires-Dist: sphinx>=4.0
Provides-Extra: ci
Requires-Dist: pytest-clarity; extra == 'ci'
Requires-Dist: pytest-subtests; extra == 'ci'
Provides-Extra: dev
Provides-Extra: test
Requires-Dist: pytest-cov; extra == 'test'
Requires-Dist: pytest>=6.0; extra == 'test'
